guppy/__init__.py
guppy/_version.py
guppy/etc/Cat.py
guppy/etc/Code.py
guppy/etc/Descriptor.py
guppy/etc/FSA.py
guppy/etc/Glue.py
guppy/etc/Help.py
guppy/etc/IterPermute.py
guppy/etc/KanExtension.py
guppy/etc/KnuthBendix.py
guppy/etc/RE.py
guppy/etc/RE_Rect.py
guppy/etc/__init__.py
guppy/etc/cmd.py
guppy/etc/etc.py
guppy/etc/textView.py
guppy/etc/tkcursors.py
guppy/etc/xterm.py
guppy/gsl/Document.py
guppy/gsl/DottedTree.py
guppy/gsl/Exceptions.py
guppy/gsl/FileIO.py
guppy/gsl/Filer.py
guppy/gsl/Gsml.py
guppy/gsl/Help.py
guppy/gsl/Html.py
guppy/gsl/Latex.py
guppy/gsl/Main.py
guppy/gsl/SpecNodes.py
guppy/gsl/Tester.py
guppy/gsl/Text.py
guppy/gsl/XHTML.py
guppy/gsl/__init__.py
guppy/heapy/Classifiers.py
guppy/heapy/Console.py
guppy/heapy/Doc.py
guppy/heapy/ImpSet.py
guppy/heapy/OutputHandling.py
guppy/heapy/Part.py
guppy/heapy/Path.py
guppy/heapy/Prof.py
guppy/heapy/RefPat.py
guppy/heapy/Spec.py
guppy/heapy/Target.py
guppy/heapy/UniSet.py
guppy/heapy/Use.py
guppy/heapy/View.py
guppy/heapy/__init__.py
guppy/heapy/heapyc.cpython-311-x86_64-linux-musl.so
guppy/heapy/pbhelp.py
guppy/heapy/test/__init__.py
guppy/heapy/test/support.py
guppy/heapy/test/test_Classifiers.py
guppy/heapy/test/test_ER.py
guppy/heapy/test/test_OutputHandling.py
guppy/heapy/test/test_Part.py
guppy/heapy/test/test_Path.py
guppy/heapy/test/test_RefPat.py
guppy/heapy/test/test_RetaGraph.py
guppy/heapy/test/test_Spec.py
guppy/heapy/test/test_UniSet.py
guppy/heapy/test/test_View.py
guppy/heapy/test/test_all.py
guppy/heapy/test/test_dependencies.py
guppy/heapy/test/test_gsl.py
guppy/heapy/test/test_heapyc.py
guppy/heapy/test/test_menuleak.py
guppy/heapy/test/test_sf.py
guppy/sets/__init__.py
guppy/sets/setsc.cpython-311-x86_64-linux-musl.so
guppy/sets/test.py
guppy3-3.1.6.dist-info/METADATA
guppy3-3.1.6.dist-info/WHEEL
guppy3-3.1.6.dist-info/top_level.txt
guppy3-3.1.6.dist-info/RECORD
guppy3-3.1.6.dist-info/licenses/LICENSE
