Metadata-Version: 2.4
Name: guppy3
Version: 3.1.6
Summary: Guppy 3 -- Guppy-PE ported to Python 3
Home-page: https://github.com/zhuyifei1999/guppy3/
Author: YiFei Zhu
Author-email: zhuyifei1999@gmail.com
License: MIT
Classifier: Programming Language :: Python :: 3
Classifier: Programming Language :: Python :: Implementation :: CPython
Classifier: Programming Language :: C
Classifier: Operating System :: OS Independent
Classifier: Development Status :: 4 - Beta
Classifier: Topic :: Software Development :: Debuggers
Classifier: Environment :: Console
Classifier: Intended Audience :: Developers
Requires-Python: >=3.10
License-File: LICENSE
Dynamic: author
Dynamic: author-email
Dynamic: classifier
Dynamic: description
Dynamic: description-content-type
Dynamic: home-page
Dynamic: license
Dynamic: license-file
Dynamic: requires-python
Dynamic: summary
